{
  "ceo": "John T. Stankey",
  "query": "John T. Stankey (diversity OR inclusion OR equity OR DEI OR belonging OR LGBTQ OR inclusive OR social responsibility)",
  "search_results": {
    "kind": "youtube#searchListResponse",
    "etag": "ZsA-kIVmeJm-2_t4HCeFZfbIZ54",
    "regionCode": "DE",
    "pageInfo": {
      "totalResults": 15,
      "resultsPerPage": 13
    },
    "items": [
      {
        "kind": "youtube#searchResult",
        "etag": "ktsdkzaKLY981fEI5KdLpoBu704",
        "id": {
          "kind": "youtube#video",
          "videoId": "7CXR54QaDl8"
        },
        "snippet": {
          "publishedAt": "2022-09-06T22:45:00Z",
          "channelId": "UC6wBro4B4pf9xnBh9Xi2zcQ",
          "title": "This CEO Fired Thousands &amp; Got $16 Million In Bonuses. AT&amp;T Stockholders Fought Back - &amp; Lost!",
          "description": "This is not a new story. It's been going on for a long time. In 1986 AT&T Chairman Robert Allen successfully defended his $16 ...",
          "thumbnails": {
            "default": {
              "url": "https://i.ytimg.com/vi/7CXR54QaDl8/default.jpg",
              "width": 120,
              "height": 90
            },
            "medium": {
              "url": "https://i.ytimg.com/vi/7CXR54QaDl8/mqdefault.jpg",
              "width": 320,
              "height": 180
            },
            "high": {
              "url": "https://i.ytimg.com/vi/7CXR54QaDl8/hqdefault.jpg",
              "width": 480,
              "height": 360
            }
          },
          "channelTitle": "David Hoffman",
          "liveBroadcastContent": "none",
          "publishTime": "2022-09-06T22:45:00Z"
        }
      },
      {
        "kind": "youtube#searchResult",
        "etag": "Vl9EC1IvAY_jU8ab9dAb_EGOdFM",
        "id": {
          "kind": "youtube#video",
          "videoId": "jQvXH_EBZQ0"
        },
        "snippet": {
          "publishedAt": "2022-02-02T22:00:13Z",
          "channelId": "UCIzXayRP7-P0ANpq-nD-h5g",
          "title": "Brave female customer tackles armed robber at east London shop #Shorts",
          "description": "Short #DRAMATIC Moment a brave customer tackles an armed would-be robber attempting to raid a convenience store in east ...",
          "thumbnails": {
            "default": {
              "url": "https://i.ytimg.com/vi/jQvXH_EBZQ0/default.jpg",
              "width": 120,
              "height": 90
            },
            "medium": {
              "url": "https://i.ytimg.com/vi/jQvXH_EBZQ0/mqdefault.jpg",
              "width": 320,
              "height": 180
            },
            "high": {
              "url": "https://i.ytimg.com/vi/jQvXH_EBZQ0/hqdefault.jpg",
              "width": 480,
              "height": 360
            }
          },
          "channelTitle": "The Sun",
          "liveBroadcastContent": "none",
          "publishTime": "2022-02-02T22:00:13Z"
        }
      },
      {
        "kind": "youtube#searchResult",
        "etag": "7H1bMPAkVIfgMaao5xWv2__faDo",
        "id": {
          "kind": "youtube#video",
          "videoId": "Z1YYB7PKI7s"
        },
        "snippet": {
          "publishedAt": "2022-07-22T04:49:26Z",
          "channelId": "UCgCh-2AfEBtWrNBC2OoNQYg",
          "title": "Is AT&amp;T Stock DEAD!? | AT&amp;T (T) Stock Analysis! |",
          "description": "Link to download my stock valuation spreadsheets: https://www.patreon.com/dividendology AT&T recently released their earnings ...",
          "thumbnails": {
            "default": {
              "url": "https://i.ytimg.com/vi/Z1YYB7PKI7s/default.jpg",
              "width": 120,
              "height": 90
            },
            "medium": {
              "url": "https://i.ytimg.com/vi/Z1YYB7PKI7s/mqdefault.jpg",
              "width": 320,
              "height": 180
            },
            "high": {
              "url": "https://i.ytimg.com/vi/Z1YYB7PKI7s/hqdefault.jpg",
              "width": 480,
              "height": 360
            }
          },
          "channelTitle": "Dividendology",
          "liveBroadcastContent": "none",
          "publishTime": "2022-07-22T04:49:26Z"
        }
      },
      {
        "kind": "youtube#searchResult",
        "etag": "9xXfFbK7kAEXTumFfMnHPdS8RxM",
        "id": {
          "kind": "youtube#video",
          "videoId": "1jbpmc6gE5c"
        },
        "snippet": {
          "publishedAt": "2022-03-29T14:15:00Z",
          "channelId": "UCSglJMvX-zSgv3PEJIE_inw",
          "title": "AT&amp;T Stock Analysis - Stock Dividend &amp; Cash Dividend Update",
          "description": "NEW! Access our Investing Website & Private Community: https://investorsgrow.com/ Robinhood Sign Up: ...",
          "thumbnails": {
            "default": {
              "url": "https://i.ytimg.com/vi/1jbpmc6gE5c/default.jpg",
              "width": 120,
              "height": 90
            },
            "medium": {
              "url": "https://i.ytimg.com/vi/1jbpmc6gE5c/mqdefault.jpg",
              "width": 320,
              "height": 180
            },
            "high": {
              "url": "https://i.ytimg.com/vi/1jbpmc6gE5c/hqdefault.jpg",
              "width": 480,
              "height": 360
            }
          },
          "channelTitle": "Learn to Invest - Investors Grow",
          "liveBroadcastContent": "none",
          "publishTime": "2022-03-29T14:15:00Z"
        }
      },
      {
        "kind": "youtube#searchResult",
        "etag": "Pb4RH9c4Ze9_3BHDZhvzfJnmnG8",
        "id": {
          "kind": "youtube#video",
          "videoId": "9bvpjdtFaQY"
        },
        "snippet": {
          "publishedAt": "2022-10-24T13:00:37Z",
          "channelId": "UCgCh-2AfEBtWrNBC2OoNQYg",
          "title": "Is AT&amp;T Stock a Buy Now!? | AT&amp;T (T) Stock Analysis! |",
          "description": "Link to download my stock valuation spreadsheets: https://www.patreon.com/dividendology Get up to 12 free stocks now using my ...",
          "thumbnails": {
            "default": {
              "url": "https://i.ytimg.com/vi/9bvpjdtFaQY/default.jpg",
              "width": 120,
              "height": 90
            },
            "medium": {
              "url": "https://i.ytimg.com/vi/9bvpjdtFaQY/mqdefault.jpg",
              "width": 320,
              "height": 180
            },
            "high": {
              "url": "https://i.ytimg.com/vi/9bvpjdtFaQY/hqdefault.jpg",
              "width": 480,
              "height": 360
            }
          },
          "channelTitle": "Dividendology",
          "liveBroadcastContent": "none",
          "publishTime": "2022-10-24T13:00:37Z"
        }
      },
      {
        "kind": "youtube#searchResult",
        "etag": "QIK_B8WM2doGo1XBl7e_Woar7u8",
        "id": {
          "kind": "youtube#video",
          "videoId": "bhdhGaQpgIk"
        },
        "snippet": {
          "publishedAt": "2022-06-04T19:06:00Z",
          "channelId": "UC-FHLCZx2Eiapx5wPnkkMMw",
          "title": "AT&amp;T Stock - An Inflation Hedge Paying a Hefty Dividend ? | T Stock",
          "description": "AT&T Stock - An Inflation Hedge Paying a Hefty Dividend ? | T Stock --- BECOME A PATREON AND GAIN FULL ACCESS TO ...",
          "thumbnails": {
            "default": {
              "url": "https://i.ytimg.com/vi/bhdhGaQpgIk/default.jpg",
              "width": 120,
              "height": 90
            },
            "medium": {
              "url": "https://i.ytimg.com/vi/bhdhGaQpgIk/mqdefault.jpg",
              "width": 320,
              "height": 180
            },
            "high": {
              "url": "https://i.ytimg.com/vi/bhdhGaQpgIk/hqdefault.jpg",
              "width": 480,
              "height": 360
            }
          },
          "channelTitle": "Investors Heaven",
          "liveBroadcastContent": "none",
          "publishTime": "2022-06-04T19:06:00Z"
        }
      },
      {
        "kind": "youtube#searchResult",
        "etag": "HiYITAWRUW5qiEwjdRwQRG2NiXE",
        "id": {
          "kind": "youtube#video",
          "videoId": "anxiiPGlFfM"
        },
        "snippet": {
          "publishedAt": "2022-04-12T10:09:29Z",
          "channelId": "UCPcc1MbakHpB8F1vIDvUJBg",
          "title": "What does the WarnerMedia-Discovery merger mean for AEW?: Wrestling Observer Radio",
          "description": "Now that WarnerMedia and Discovery have merged to form Warner Bros. Discovery, Bryan and Dave discuss what it could mean ...",
          "thumbnails": {
            "default": {
              "url": "https://i.ytimg.com/vi/anxiiPGlFfM/default.jpg",
              "width": 120,
              "height": 90
            },
            "medium": {
              "url": "https://i.ytimg.com/vi/anxiiPGlFfM/mqdefault.jpg",
              "width": 320,
              "height": 180
            },
            "high": {
              "url": "https://i.ytimg.com/vi/anxiiPGlFfM/hqdefault.jpg",
              "width": 480,
              "height": 360
            }
          },
          "channelTitle": "F4WOnline",
          "liveBroadcastContent": "none",
          "publishTime": "2022-04-12T10:09:29Z"
        }
      },
      {
        "kind": "youtube#searchResult",
        "etag": "UZpvy6GDSki19v_uKBa8cux_gq4",
        "id": {
          "kind": "youtube#video",
          "videoId": "dBUhiQUGYg8"
        },
        "snippet": {
          "publishedAt": "2022-02-04T19:06:38Z",
          "channelId": "UCgCh-2AfEBtWrNBC2OoNQYg",
          "title": "BIG AT&amp;T STOCK NEWS! | AT&amp;T Stock Analysis |",
          "description": "Link to download my portfolio tracking spreadsheets: https://www.patreon.com/dividendology In this video, we cover some new ...",
          "thumbnails": {
            "default": {
              "url": "https://i.ytimg.com/vi/dBUhiQUGYg8/default.jpg",
              "width": 120,
              "height": 90
            },
            "medium": {
              "url": "https://i.ytimg.com/vi/dBUhiQUGYg8/mqdefault.jpg",
              "width": 320,
              "height": 180
            },
            "high": {
              "url": "https://i.ytimg.com/vi/dBUhiQUGYg8/hqdefault.jpg",
              "width": 480,
              "height": 360
            }
          },
          "channelTitle": "Dividendology",
          "liveBroadcastContent": "none",
          "publishTime": "2022-02-04T19:06:38Z"
        }
      },
      {
        "kind": "youtube#searchResult",
        "etag": "5iNUinYd4qNUXBU3dcNTUzUiuA0",
        "id": {
          "kind": "youtube#video",
          "videoId": "XiTqEXr5Uws"
        },
        "snippet": {
          "publishedAt": "2022-02-27T12:33:43Z",
          "channelId": "UCatSwCHVd7hhEVOoQnODfVg",
          "title": "Warner Bros Discovery - Stock Analysis - $WBD",
          "description": "WBD Warner Bros Discovery is a global entertainment company that produces TV networks, feature length theatrical releases, ...",
          "thumbnails": {
            "default": {
              "url": "https://i.ytimg.com/vi/XiTqEXr5Uws/default.jpg",
              "width": 120,
              "height": 90
            },
            "medium": {
              "url": "https://i.ytimg.com/vi/XiTqEXr5Uws/mqdefault.jpg",
              "width": 320,
              "height": 180
            },
            "high": {
              "url": "https://i.ytimg.com/vi/XiTqEXr5Uws/hqdefault.jpg",
              "width": 480,
              "height": 360
            }
          },
          "channelTitle": "Midas Investing",
          "liveBroadcastContent": "none",
          "publishTime": "2022-02-27T12:33:43Z"
        }
      },
      {
        "kind": "youtube#searchResult",
        "etag": "eAcbM3HcD46e1VMTczAVeAhyjZo",
        "id": {
          "kind": "youtube#video",
          "videoId": "cGZboJ7hZMk"
        },
        "snippet": {
          "publishedAt": "2022-02-03T00:08:28Z",
          "channelId": "UCHDRBmhUBNr5gZLpLZ1pi6Q",
          "title": "GE Still Has a Long Ways to Go | GE Stock Analysis",
          "description": "In this video, I reviewed GE's most recent Earnings updates and the current financial position and value of the stock. Get a Free ...",
          "thumbnails": {
            "default": {
              "url": "https://i.ytimg.com/vi/cGZboJ7hZMk/default.jpg",
              "width": 120,
              "height": 90
            },
            "medium": {
              "url": "https://i.ytimg.com/vi/cGZboJ7hZMk/mqdefault.jpg",
              "width": 320,
              "height": 180
            },
            "high": {
              "url": "https://i.ytimg.com/vi/cGZboJ7hZMk/hqdefault.jpg",
              "width": 480,
              "height": 360
            }
          },
          "channelTitle": "Nick Daly",
          "liveBroadcastContent": "none",
          "publishTime": "2022-02-03T00:08:28Z"
        }
      },
      {
        "kind": "youtube#searchResult",
        "etag": "R4qcx0snHstphCLdJfsKhsW4ziM",
        "id": {
          "kind": "youtube#video",
          "videoId": "08AUMLea6mk"
        },
        "snippet": {
          "publishedAt": "2022-10-01T20:00:00Z",
          "channelId": "UChBVf9YnourrEDTsbbwJPRA",
          "title": "3 stocks at 52 Wk Low! | Mastercard, AT&amp;T, UPS stock analysis",
          "description": "Today, I'm going to analyze 3 stocks at 52 wk low. We'll get into the fundamentals of Mastercard, AT&T and UPS stock to see if ...",
          "thumbnails": {
            "default": {
              "url": "https://i.ytimg.com/vi/08AUMLea6mk/default.jpg",
              "width": 120,
              "height": 90
            },
            "medium": {
              "url": "https://i.ytimg.com/vi/08AUMLea6mk/mqdefault.jpg",
              "width": 320,
              "height": 180
            },
            "high": {
              "url": "https://i.ytimg.com/vi/08AUMLea6mk/hqdefault.jpg",
              "width": 480,
              "height": 360
            }
          },
          "channelTitle": "Everything Money",
          "liveBroadcastContent": "none",
          "publishTime": "2022-10-01T20:00:00Z"
        }
      },
      {
        "kind": "youtube#searchResult",
        "etag": "GMZDIXNVyXDtcDQH86sj6eED1P0",
        "id": {
          "kind": "youtube#video",
          "videoId": "lOBFkxOz7YE"
        },
        "snippet": {
          "publishedAt": "2022-02-10T16:00:17Z",
          "channelId": "UCHDRBmhUBNr5gZLpLZ1pi6Q",
          "title": "SNAP Stock Is Headed Higher | SNAP Stock Analysis",
          "description": "In this video, I reviewed SNAP Stock most recent Earnings updates and the current financial position and value of the stock.",
          "thumbnails": {
            "default": {
              "url": "https://i.ytimg.com/vi/lOBFkxOz7YE/default.jpg",
              "width": 120,
              "height": 90
            },
            "medium": {
              "url": "https://i.ytimg.com/vi/lOBFkxOz7YE/mqdefault.jpg",
              "width": 320,
              "height": 180
            },
            "high": {
              "url": "https://i.ytimg.com/vi/lOBFkxOz7YE/hqdefault.jpg",
              "width": 480,
              "height": 360
            }
          },
          "channelTitle": "Nick Daly",
          "liveBroadcastContent": "none",
          "publishTime": "2022-02-10T16:00:17Z"
        }
      },
      {
        "kind": "youtube#searchResult",
        "etag": "YeABuG3zVn_dxjAxES0GTc-d2Zs",
        "id": {
          "kind": "youtube#video",
          "videoId": "fc260Ke6Zk8"
        },
        "snippet": {
          "publishedAt": "2022-02-06T16:53:19Z",
          "channelId": "UCbcB_-Hn75TrZUP4nZX4jow",
          "title": "#DWAC \ud83d\udd25Trump Social Media App Launch Soon! #DWACW \ud83d\udd25 #PHUN \ud83d\udd25 #CFVI \ud83d\udd25 Should you enter before run-up?",
          "description": "DWAC #PHUN #CFVI Please join my Patreon and get access to Discord to get daily trade ideas, instant notifications, and live ...",
          "thumbnails": {
            "default": {
              "url": "https://i.ytimg.com/vi/fc260Ke6Zk8/default.jpg",
              "width": 120,
              "height": 90
            },
            "medium": {
              "url": "https://i.ytimg.com/vi/fc260Ke6Zk8/mqdefault.jpg",
              "width": 320,
              "height": 180
            },
            "high": {
              "url": "https://i.ytimg.com/vi/fc260Ke6Zk8/hqdefault.jpg",
              "width": 480,
              "height": 360
            }
          },
          "channelTitle": "Da Stock Analyst",
          "liveBroadcastContent": "none",
          "publishTime": "2022-02-06T16:53:19Z"
        }
      }
    ]
  },
  "video_details": {
    "kind": "youtube#videoListResponse",
    "etag": "Cpin3AJ2RBtoCpH5GxAQ7Eq4nIU",
    "items": [
      {
        "kind": "youtube#video",
        "etag": "v0-kMJDG7N5VB1eD-NNP7b8IXRI",
        "id": "7CXR54QaDl8",
        "snippet": {
          "publishedAt": "2022-09-06T22:45:00Z",
          "channelId": "UC6wBro4B4pf9xnBh9Xi2zcQ",
          "title": "This CEO Fired Thousands & Got $16 Million In Bonuses. AT&T Stockholders Fought Back - & Lost!",
          "description": "This is not a new story. It's been going on for a long time. In 1986 AT&T Chairman Robert Allen successfully defended his $16 million pay package at the phone company's annual shareholders meeting. He was unapologetic about his pay or his attempts to streamline the company by firing 40,000 people. In the late 1980s, corporations like AT&T pushed to tie executive pay more closely to the company's profits and stock performance without caring for how the employees fared.\n\nThis report was made one year before the 1987 bank crisis that bankrupted most of the small entrepreneurs I know in Maine where I lived. It's where I learned that I was no good at buying and selling stocks and was never \"ahead of the game\" played by those who manipulated the markets.\n\nI was a freelance filmmaker back then and did a good deal of work for AT&T. I knew some of the 40,000 people who got fired and felt for them. This is not a film that I made (or would've made). This report was presented on PBS by host Paul Salmon. \n\nCEO compensation versus employee compensation is still an issue today and has not improved. The Board of Directors wants to make money for the stockholders as is their charge they feel that that is more likely to happen if they reward senior management and especially the CEO not caring about the employees and how they are treated.\n\nThis is not how corporations treated companies when I started my career in the 1960s. Company CEOs who I worked with care as much for how the employees were treated and felt as they did for the stockholders, or at least that's how it appeared to me.\n\nIf you have a similar story that happened to you or someone you know, please share it by commenting on this video.\nThank you\nDavid Hoffman filmmaker",
          "thumbnails": {
            "default": {
              "url": "https://i.ytimg.com/vi/7CXR54QaDl8/default.jpg",
              "width": 120,
              "height": 90
            },
            "medium": {
              "url": "https://i.ytimg.com/vi/7CXR54QaDl8/mqdefault.jpg",
              "width": 320,
              "height": 180
            },
            "high": {
              "url": "https://i.ytimg.com/vi/7CXR54QaDl8/hqdefault.jpg",
              "width": 480,
              "height": 360
            },
            "standard": {
              "url": "https://i.ytimg.com/vi/7CXR54QaDl8/sddefault.jpg",
              "width": 640,
              "height": 480
            }
          },
          "channelTitle": "David Hoffman",
          "tags": [
            "Corporate bonus",
            "CEO bonus",
            "capitalism",
            "employee pay cut",
            "employees fired",
            "Fortune 500 stories",
            "1980s corporations",
            "1980s pay",
            "David Hoffman filmmaker",
            "stock market",
            "business news",
            "finance stock",
            "finance news",
            "money tips",
            "stock market news",
            "stock market analysis",
            "financial stocks to buy",
            "AT&T history",
            "Robert Allen CEO",
            "corporate CEO",
            "making money in the markets",
            "AT&T stock price",
            "shareholder revolt",
            "shareholders fight back",
            "finance news usa",
            "making money in stock"
          ],
          "categoryId": "22",
          "liveBroadcastContent": "none",
          "defaultLanguage": "en",
          "localized": {
            "title": "This CEO Fired Thousands & Got $16 Million In Bonuses. AT&T Stockholders Fought Back - & Lost!",
            "description": "This is not a new story. It's been going on for a long time. In 1986 AT&T Chairman Robert Allen successfully defended his $16 million pay package at the phone company's annual shareholders meeting. He was unapologetic about his pay or his attempts to streamline the company by firing 40,000 people. In the late 1980s, corporations like AT&T pushed to tie executive pay more closely to the company's profits and stock performance without caring for how the employees fared.\n\nThis report was made one year before the 1987 bank crisis that bankrupted most of the small entrepreneurs I know in Maine where I lived. It's where I learned that I was no good at buying and selling stocks and was never \"ahead of the game\" played by those who manipulated the markets.\n\nI was a freelance filmmaker back then and did a good deal of work for AT&T. I knew some of the 40,000 people who got fired and felt for them. This is not a film that I made (or would've made). This report was presented on PBS by host Paul Salmon. \n\nCEO compensation versus employee compensation is still an issue today and has not improved. The Board of Directors wants to make money for the stockholders as is their charge they feel that that is more likely to happen if they reward senior management and especially the CEO not caring about the employees and how they are treated.\n\nThis is not how corporations treated companies when I started my career in the 1960s. Company CEOs who I worked with care as much for how the employees were treated and felt as they did for the stockholders, or at least that's how it appeared to me.\n\nIf you have a similar story that happened to you or someone you know, please share it by commenting on this video.\nThank you\nDavid Hoffman filmmaker"
          },
          "defaultAudioLanguage": "es-419"
        },
        "contentDetails": {
          "duration": "PT7M14S",
          "dimension": "2d",
          "definition": "sd",
          "caption": "false",
          "licensedContent": true,
          "contentRating": {},
          "projection": "rectangular"
        },
        "statistics": {
          "viewCount": "11635",
          "likeCount": "445",
          "favoriteCount": "0",
          "commentCount": "117"
        }
      },
      {
        "kind": "youtube#video",
        "etag": "NbGJvy0CPYaRvFZqGuSv9waokIs",
        "id": "jQvXH_EBZQ0",
        "snippet": {
          "publishedAt": "2022-02-02T22:00:13Z",
          "channelId": "UCIzXayRP7-P0ANpq-nD-h5g",
          "title": "Brave female customer tackles armed robber at east London shop #Shorts",
          "description": "#Short #DRAMATIC Moment a brave customer tackles an armed would-be robber attempting to raid a convenience store in east London. \n\nThe thug brandished what reassembled a knife at the shop assistant behind the counter, before the brave woman thwarted his attempts by restraining him. \n\nCCTV footage from the store shows the armed thug running from the store when he quickly realises his attack was futile. \n\nThe Sun newspaper brings you the latest breaking news videos and explainers from the UK and around the world\n\nThe Sun brings you breaking news and in-depth analysis on the stories that matter most. From the ongoing war in Ukraine to conflicts in the Middle East and US and UK politics, we post updates as they happen. Expect the latest on major global events, pressing political debates, celebrity updates and exclusive royal family content, along with in-depth investigations and expert commentary. Get comprehensive coverage of Donald Trump's Presidency, Vladimir Putin's actions, and the unfolding drama of the British Royal Family. \n\nSubscribe now for daily updates and exclusive content from The Sun.\nhttps://www.youtube.com/c/thesun?sub_confirmation=1\n\nRead The Sun: https://bit.ly/3Tay1OY\nLike The Sun on Facebook: https://www.facebook.com/thesun/\nFollow The Sun on TikTok: https://www.tiktok.com/@UCIzXayRP7-P0ANpq-nD-h5g\nSubscribe to The Sun on Snapchat: https://www.snapchat.com/discover/The_Sun/1633225139\n#Shorts",
          "thumbnails": {
            "default": {
              "url": "https://i.ytimg.com/vi/jQvXH_EBZQ0/default.jpg",
              "width": 120,
              "height": 90
            },
            "medium": {
              "url": "https://i.ytimg.com/vi/jQvXH_EBZQ0/mqdefault.jpg",
              "width": 320,
              "height": 180
            },
            "high": {
              "url": "https://i.ytimg.com/vi/jQvXH_EBZQ0/hqdefault.jpg",
              "width": 480,
              "height": 360
            },
            "standard": {
              "url": "https://i.ytimg.com/vi/jQvXH_EBZQ0/sddefault.jpg",
              "width": 640,
              "height": 480
            },
            "maxres": {
              "url": "https://i.ytimg.com/vi/jQvXH_EBZQ0/maxresdefault.jpg",
              "width": 1280,
              "height": 720
            }
          },
          "channelTitle": "The Sun",
          "tags": [
            "The Sun",
            "news",
            "breaking news",
            "attack",
            "theif",
            "robber",
            "robbery",
            "day light robbery",
            "east London",
            "london",
            "london news",
            "east london news",
            "shorts",
            "short",
            "short video",
            "Sun shorts",
            "womna",
            "brave",
            "customer",
            "shop",
            "shop raid",
            "raid"
          ],
          "categoryId": "25",
          "liveBroadcastContent": "none",
          "defaultLanguage": "en-GB",
          "localized": {
            "title": "Brave female customer tackles armed robber at east London shop #Shorts",
            "description": "#Short #DRAMATIC Moment a brave customer tackles an armed would-be robber attempting to raid a convenience store in east London. \n\nThe thug brandished what reassembled a knife at the shop assistant behind the counter, before the brave woman thwarted his attempts by restraining him. \n\nCCTV footage from the store shows the armed thug running from the store when he quickly realises his attack was futile. \n\nThe Sun newspaper brings you the latest breaking news videos and explainers from the UK and around the world\n\nThe Sun brings you breaking news and in-depth analysis on the stories that matter most. From the ongoing war in Ukraine to conflicts in the Middle East and US and UK politics, we post updates as they happen. Expect the latest on major global events, pressing political debates, celebrity updates and exclusive royal family content, along with in-depth investigations and expert commentary. Get comprehensive coverage of Donald Trump's Presidency, Vladimir Putin's actions, and the unfolding drama of the British Royal Family. \n\nSubscribe now for daily updates and exclusive content from The Sun.\nhttps://www.youtube.com/c/thesun?sub_confirmation=1\n\nRead The Sun: https://bit.ly/3Tay1OY\nLike The Sun on Facebook: https://www.facebook.com/thesun/\nFollow The Sun on TikTok: https://www.tiktok.com/@UCIzXayRP7-P0ANpq-nD-h5g\nSubscribe to The Sun on Snapchat: https://www.snapchat.com/discover/The_Sun/1633225139\n#Shorts"
          },
          "defaultAudioLanguage": "en-GB"
        },
        "contentDetails": {
          "duration": "PT37S",
          "dimension": "2d",
          "definition": "hd",
          "caption": "false",
          "licensedContent": true,
          "contentRating": {},
          "projection": "rectangular"
        },
        "statistics": {
          "viewCount": "51393919",
          "likeCount": "1003448",
          "favoriteCount": "0",
          "commentCount": "25118"
        }
      },
      {
        "kind": "youtube#video",
        "etag": "kGZ6jfpyBwmzn0_t-vE8w0xO34s",
        "id": "Z1YYB7PKI7s",
        "snippet": {
          "publishedAt": "2022-07-22T04:49:26Z",
          "channelId": "UCgCh-2AfEBtWrNBC2OoNQYg",
          "title": "Is AT&T Stock DEAD!? | AT&T (T) Stock Analysis! |",
          "description": "Link to download my stock valuation spreadsheets:\nhttps://www.patreon.com/dividendology\n\nAT&T recently released their earnings report. In this video, we go over the earnings report and perform a complete stock analysis on the company. Let me know what your thoughts on this company are in the comments below!\n\n\nFollow me on Twitter: https://twitter.com/dividendology\nJoin my Discord! https://www.patreon.com/dividendology\n\n\nI am not a Financial advisor or licensed professional. Nothing I say or produce on YouTube, or anywhere else, should be considered as advice. All content is for educational purposes only. I am not responsible for any financial losses or gains. Invest and trade at your own risk.",
          "thumbnails": {
            "default": {
              "url": "https://i.ytimg.com/vi/Z1YYB7PKI7s/default.jpg",
              "width": 120,
              "height": 90
            },
            "medium": {
              "url": "https://i.ytimg.com/vi/Z1YYB7PKI7s/mqdefault.jpg",
              "width": 320,
              "height": 180
            },
            "high": {
              "url": "https://i.ytimg.com/vi/Z1YYB7PKI7s/hqdefault.jpg",
              "width": 480,
              "height": 360
            },
            "standard": {
              "url": "https://i.ytimg.com/vi/Z1YYB7PKI7s/sddefault.jpg",
              "width": 640,
              "height": 480
            },
            "maxres": {
              "url": "https://i.ytimg.com/vi/Z1YYB7PKI7s/maxresdefault.jpg",
              "width": 1280,
              "height": 720
            }
          },
          "channelTitle": "Dividendology",
          "tags": [
            "stock market",
            "t stock",
            "at&t stock",
            "stocks",
            "stock",
            "at&t stock analysis",
            "t stock analysis",
            "att stock",
            "dividend stocks",
            "stock market news",
            "stocks to buy",
            "stocks to buy now",
            "at&t stock news",
            "stock analysis",
            "at&t stock price",
            "stocks 2022",
            "att stock 2022",
            "finance stock",
            "at&t stock dividend",
            "stock analyzer",
            "stocks channel",
            "dividend stocks 2022",
            "dividend stocks to buy",
            "is t stock a buy",
            "t stock dividend",
            "stock market crash",
            "stock fundamental analysis",
            "AT&T earnings",
            "T earnings"
          ],
          "categoryId": "27",
          "liveBroadcastContent": "none",
          "defaultLanguage": "en",
          "localized": {
            "title": "Is AT&T Stock DEAD!? | AT&T (T) Stock Analysis! |",
            "description": "Link to download my stock valuation spreadsheets:\nhttps://www.patreon.com/dividendology\n\nAT&T recently released their earnings report. In this video, we go over the earnings report and perform a complete stock analysis on the company. Let me know what your thoughts on this company are in the comments below!\n\n\nFollow me on Twitter: https://twitter.com/dividendology\nJoin my Discord! https://www.patreon.com/dividendology\n\n\nI am not a Financial advisor or licensed professional. Nothing I say or produce on YouTube, or anywhere else, should be considered as advice. All content is for educational purposes only. I am not responsible for any financial losses or gains. Invest and trade at your own risk."
          }
        },
        "contentDetails": {
          "duration": "PT6M49S",
          "dimension": "2d",
          "definition": "hd",
          "caption": "false",
          "licensedContent": true,
          "contentRating": {},
          "projection": "rectangular"
        },
        "statistics": {
          "viewCount": "3711",
          "likeCount": "164",
          "favoriteCount": "0",
          "commentCount": "20"
        }
      },
      {
        "kind": "youtube#video",
        "etag": "5Es7WA8ufGf3xQ2thZcX8rkvqKM",
        "id": "1jbpmc6gE5c",
        "snippet": {
          "publishedAt": "2022-03-29T14:15:00Z",
          "channelId": "UCSglJMvX-zSgv3PEJIE_inw",
          "title": "AT&T Stock Analysis - Stock Dividend & Cash Dividend Update",
          "description": "NEW! Access our Investing Website & Private Community: https://investorsgrow.com/ \n\nRobinhood Sign Up: https://join.robinhood.com/jamesc10724\n\n\u2605\u2606\u2605 Subscribe: \u2605\u2606\u2605\nhttps://goo.gl/qkRHDf \n\nInvesting Basics Playlist\nhttps://goo.gl/ky7CJq\n\nInvesting Books I like: \nThe Intelligent Investor - https://amzn.to/2PVhfEL\nCommon Stocks & Uncommon Profits - https://amzn.to/2DAV8h9\nUnderstanding Options -  https://amzn.to/2T9gFSp\nLittle Book of Common Sense Investing - https://amzn.to/2DfFGG2\nHow to Value Exchange-Traded Funds - https://amzn.to/2PWSkRg\nA Great Book on Building Wealth - https://amzn.to/2T8AKZ1\nDale Carnegie - https://amzn.to/2DDAk8w\nEffective Speaking - https://amzn.to/2DBncAT\nAudible Membership I Use (Audio Books): https://amzn.to/2LCorAY\n\nEquipment I Use:\nMicrophone - https://amzn.to/2T7JxL6\nVideo Editing Software - https://amzn.to/2RQM1vE\nThumbnail Editing Software - https://amzn.to/2qIUAgP\nLaptop - https://amzn.to/2T4xA8Z\n\nDISCLAIMER: I am not a financial advisor. These videos are for educational purposes only. Investing of any kind involves risk. Your investments are solely your responsibility and we do not provide personalized investment advice. It is crucial that you conduct your own research. I am merely sharing my opinion with no guarantee of gains or losses on investments. Please consult your financial or tax professional prior to making an investment.\n\n#LearnToInvest #StocksToWatch #StockMarket",
          "thumbnails": {
            "default": {
              "url": "https://i.ytimg.com/vi/1jbpmc6gE5c/default.jpg",
              "width": 120,
              "height": 90
            },
            "medium": {
              "url": "https://i.ytimg.com/vi/1jbpmc6gE5c/mqdefault.jpg",
              "width": 320,
              "height": 180
            },
            "high": {
              "url": "https://i.ytimg.com/vi/1jbpmc6gE5c/hqdefault.jpg",
              "width": 480,
              "height": 360
            },
            "standard": {
              "url": "https://i.ytimg.com/vi/1jbpmc6gE5c/sddefault.jpg",
              "width": 640,
              "height": 480
            },
            "maxres": {
              "url": "https://i.ytimg.com/vi/1jbpmc6gE5c/maxresdefault.jpg",
              "width": 1280,
              "height": 720
            }
          },
          "channelTitle": "Learn to Invest - Investors Grow",
          "tags": [
            "Investment Ideas",
            "learn to invest",
            "investing for beginners",
            "stock market",
            "how to invest",
            "AT&T",
            "$T",
            "T Stock",
            "T Buy Stock",
            "T Sell Stock",
            "T Dividend",
            "AT&T Stock",
            "Buy AT&T Stock",
            "Sell AT&T Stock",
            "T Fair Value",
            "Fair value of T",
            "is T a good investment",
            "AT&T Analysis",
            "AT&T Dividend",
            "buy AT&T",
            "buy T",
            "sell AT&T",
            "sell T",
            "should I buy AT&T",
            "should I buy T",
            "warner media",
            "discovery",
            "spinoff",
            "at&t spin off",
            "at&t spinoff of warner media"
          ],
          "categoryId": "27",
          "liveBroadcastContent": "none",
          "defaultLanguage": "en",
          "localized": {
            "title": "AT&T Stock Analysis - Stock Dividend & Cash Dividend Update",
            "description": "NEW! Access our Investing Website & Private Community: https://investorsgrow.com/ \n\nRobinhood Sign Up: https://join.robinhood.com/jamesc10724\n\n\u2605\u2606\u2605 Subscribe: \u2605\u2606\u2605\nhttps://goo.gl/qkRHDf \n\nInvesting Basics Playlist\nhttps://goo.gl/ky7CJq\n\nInvesting Books I like: \nThe Intelligent Investor - https://amzn.to/2PVhfEL\nCommon Stocks & Uncommon Profits - https://amzn.to/2DAV8h9\nUnderstanding Options -  https://amzn.to/2T9gFSp\nLittle Book of Common Sense Investing - https://amzn.to/2DfFGG2\nHow to Value Exchange-Traded Funds - https://amzn.to/2PWSkRg\nA Great Book on Building Wealth - https://amzn.to/2T8AKZ1\nDale Carnegie - https://amzn.to/2DDAk8w\nEffective Speaking - https://amzn.to/2DBncAT\nAudible Membership I Use (Audio Books): https://amzn.to/2LCorAY\n\nEquipment I Use:\nMicrophone - https://amzn.to/2T7JxL6\nVideo Editing Software - https://amzn.to/2RQM1vE\nThumbnail Editing Software - https://amzn.to/2qIUAgP\nLaptop - https://amzn.to/2T4xA8Z\n\nDISCLAIMER: I am not a financial advisor. These videos are for educational purposes only. Investing of any kind involves risk. Your investments are solely your responsibility and we do not provide personalized investment advice. It is crucial that you conduct your own research. I am merely sharing my opinion with no guarantee of gains or losses on investments. Please consult your financial or tax professional prior to making an investment.\n\n#LearnToInvest #StocksToWatch #StockMarket"
          },
          "defaultAudioLanguage": "en"
        },
        "contentDetails": {
          "duration": "PT10M27S",
          "dimension": "2d",
          "definition": "hd",
          "caption": "false",
          "licensedContent": true,
          "contentRating": {},
          "projection": "rectangular"
        },
        "statistics": {
          "viewCount": "33423",
          "likeCount": "1289",
          "favoriteCount": "0",
          "commentCount": "105"
        }
      },
      {
        "kind": "youtube#video",
        "etag": "J5BXig_RZ6Kc9GerZ7YlewifB1g",
        "id": "9bvpjdtFaQY",
        "snippet": {
          "publishedAt": "2022-10-24T13:00:37Z",
          "channelId": "UCgCh-2AfEBtWrNBC2OoNQYg",
          "title": "Is AT&T Stock a Buy Now!? | AT&T (T) Stock Analysis! |",
          "description": "Link to download my stock valuation spreadsheets:\nhttps://www.patreon.com/dividendology\n\nGet up to 12 free stocks now using my link for Webull! (Free Money!!): https://a.webull.com/i/Dividendology\n\nGet 50% off of Seeking Alpha Premium!\nhttps://www.sahg6dtr.com/9D5QH2/R74QP/\n\n\nIn this video, we perform a stock analysis on AT&T. Let me know your thoughts on this company in the comments below!\n\n\n\nSocial Media (and other fun stuff): https://linktr.ee/dividendology\n\n\nI am not a Financial advisor or licensed professional. Nothing I say or produce on YouTube, or anywhere else, should be considered as advice. All content is for educational purposes only. I am not responsible for any financial losses or gains. Invest and trade at your own risk. Some of the links in the description may be affiliate links.",
          "thumbnails": {
            "default": {
              "url": "https://i.ytimg.com/vi/9bvpjdtFaQY/default.jpg",
              "width": 120,
              "height": 90
            },
            "medium": {
              "url": "https://i.ytimg.com/vi/9bvpjdtFaQY/mqdefault.jpg",
              "width": 320,
              "height": 180
            },
            "high": {
              "url": "https://i.ytimg.com/vi/9bvpjdtFaQY/hqdefault.jpg",
              "width": 480,
              "height": 360
            },
            "standard": {
              "url": "https://i.ytimg.com/vi/9bvpjdtFaQY/sddefault.jpg",
              "width": 640,
              "height": 480
            },
            "maxres": {
              "url": "https://i.ytimg.com/vi/9bvpjdtFaQY/maxresdefault.jpg",
              "width": 1280,
              "height": 720
            }
          },
          "channelTitle": "Dividendology",
          "tags": [
            "stock market",
            "stocks",
            "t stock",
            "at&t stock",
            "stocks to buy now",
            "at&t stock analysis",
            "stock market news",
            "stocks to buy",
            "t stock analysis",
            "stock",
            "att stock",
            "dividend stocks",
            "stock analysis",
            "finance stock",
            "vz stock",
            "stock market crash",
            "stocks 2022",
            "stocks channel",
            "at&t stock news",
            "is t stock a buy",
            "att stock 2022",
            "dividend stocks 2022",
            "best dividend stocks",
            "verizon stock",
            "dna stock",
            "geo stock",
            "t stock dividend",
            "at&t stock price",
            "path stock",
            "tmus stock"
          ],
          "categoryId": "27",
          "liveBroadcastContent": "none",
          "defaultLanguage": "en",
          "localized": {
            "title": "Is AT&T Stock a Buy Now!? | AT&T (T) Stock Analysis! |",
            "description": "Link to download my stock valuation spreadsheets:\nhttps://www.patreon.com/dividendology\n\nGet up to 12 free stocks now using my link for Webull! (Free Money!!): https://a.webull.com/i/Dividendology\n\nGet 50% off of Seeking Alpha Premium!\nhttps://www.sahg6dtr.com/9D5QH2/R74QP/\n\n\nIn this video, we perform a stock analysis on AT&T. Let me know your thoughts on this company in the comments below!\n\n\n\nSocial Media (and other fun stuff): https://linktr.ee/dividendology\n\n\nI am not a Financial advisor or licensed professional. Nothing I say or produce on YouTube, or anywhere else, should be considered as advice. All content is for educational purposes only. I am not responsible for any financial losses or gains. Invest and trade at your own risk. Some of the links in the description may be affiliate links."
          }
        },
        "contentDetails": {
          "duration": "PT6M47S",
          "dimension": "2d",
          "definition": "hd",
          "caption": "false",
          "licensedContent": true,
          "contentRating": {},
          "projection": "rectangular"
        },
        "statistics": {
          "viewCount": "8220",
          "likeCount": "216",
          "favoriteCount": "0",
          "commentCount": "37"
        }
      },
      {
        "kind": "youtube#video",
        "etag": "A6MKndwzqzA3iI0H_6QHWCwOngA",
        "id": "bhdhGaQpgIk",
        "snippet": {
          "publishedAt": "2022-06-04T19:06:00Z",
          "channelId": "UC-FHLCZx2Eiapx5wPnkkMMw",
          "title": "AT&T Stock - An Inflation Hedge Paying a Hefty Dividend ? | T Stock",
          "description": "AT&T Stock - An Inflation Hedge Paying a Hefty Dividend ? | T Stock\n\n--- BECOME A PATREON AND GAIN FULL ACCESS TO OUR STOCK ANALYSIS TOOL!\n\n--- JOIN US ON PATREON HERE: \nhttps://www.patreon.com/investorsheaven?fan_landing=true\n\n--- LOGIN TO OUR TOOL HERE:\nhttps://www.myinvestorsheaven.com/ \n\n--- JOIN US ON DISCORD (100% FREE) : https://discord.gg/c8HpfjRzd2\n\n--- If you are having ANY issues with the tool, you can contact me live on the discord channel above or send an email at support@myinvestorsheaven.com\n\n--- Disclaimer ---\nThe content of this video is not investment advice and does not constitute an offer or solicitation to offer or recommendation of any investment product. You should not rely upon the information on this video as a basis for making any legal, tax, or investment decisions. The owner of this Youtube Channel makes no representations or warranties of any kind, either express or implied, about the correctness, completeness, accuracy, suitability, reliability concerning the information of this video.",
          "thumbnails": {
            "default": {
              "url": "https://i.ytimg.com/vi/bhdhGaQpgIk/default.jpg",
              "width": 120,
              "height": 90
            },
            "medium": {
              "url": "https://i.ytimg.com/vi/bhdhGaQpgIk/mqdefault.jpg",
              "width": 320,
              "height": 180
            },
            "high": {
              "url": "https://i.ytimg.com/vi/bhdhGaQpgIk/hqdefault.jpg",
              "width": 480,
              "height": 360
            },
            "standard": {
              "url": "https://i.ytimg.com/vi/bhdhGaQpgIk/sddefault.jpg",
              "width": 640,
              "height": 480
            },
            "maxres": {
              "url": "https://i.ytimg.com/vi/bhdhGaQpgIk/maxresdefault.jpg",
              "width": 1280,
              "height": 720
            }
          },
          "channelTitle": "Investors Heaven",
          "categoryId": "27",
          "liveBroadcastContent": "none",
          "defaultLanguage": "en-US",
          "localized": {
            "title": "AT&T Stock - An Inflation Hedge Paying a Hefty Dividend ? | T Stock",
            "description": "AT&T Stock - An Inflation Hedge Paying a Hefty Dividend ? | T Stock\n\n--- BECOME A PATREON AND GAIN FULL ACCESS TO OUR STOCK ANALYSIS TOOL!\n\n--- JOIN US ON PATREON HERE: \nhttps://www.patreon.com/investorsheaven?fan_landing=true\n\n--- LOGIN TO OUR TOOL HERE:\nhttps://www.myinvestorsheaven.com/ \n\n--- JOIN US ON DISCORD (100% FREE) : https://discord.gg/c8HpfjRzd2\n\n--- If you are having ANY issues with the tool, you can contact me live on the discord channel above or send an email at support@myinvestorsheaven.com\n\n--- Disclaimer ---\nThe content of this video is not investment advice and does not constitute an offer or solicitation to offer or recommendation of any investment product. You should not rely upon the information on this video as a basis for making any legal, tax, or investment decisions. The owner of this Youtube Channel makes no representations or warranties of any kind, either express or implied, about the correctness, completeness, accuracy, suitability, reliability concerning the information of this video."
          },
          "defaultAudioLanguage": "en-US"
        },
        "contentDetails": {
          "duration": "PT9M30S",
          "dimension": "2d",
          "definition": "hd",
          "caption": "false",
          "licensedContent": false,
          "contentRating": {},
          "projection": "rectangular"
        },
        "statistics": {
          "viewCount": "256",
          "likeCount": "18",
          "favoriteCount": "0",
          "commentCount": "2"
        }
      },
      {
        "kind": "youtube#video",
        "etag": "gdusyPH5GOrB266820JMex3qLJ8",
        "id": "anxiiPGlFfM",
        "snippet": {
          "publishedAt": "2022-04-12T10:09:29Z",
          "channelId": "UCPcc1MbakHpB8F1vIDvUJBg",
          "title": "What does the WarnerMedia-Discovery merger mean for AEW?: Wrestling Observer Radio",
          "description": "Now that WarnerMedia and Discovery have merged to form Warner Bros. Discovery, Bryan and Dave discuss what it could mean for AEW's television deal with WarnerMedia. [April 12, 2022]\n\nDon't have access to this video? Sign up now! https://www.youtube.com/channel/UCPcc1MbakHpB8F1vIDvUJBg/join\n\nYou can see the Wrestling Observer Newsletter with a subscription here: http://account.f4wonline.com/signup\n\nWrestling Observer is live at Noon PST/3pm EST every weekday, live on Twitch! https://twitch.tv/f4wvideo \n\nGrab some awesome T Shirts here: https://www.f4wonline.com/shirts\n\nFollowing us on Twitter @WONF4W https://twitter.com/wonf4w",
          "thumbnails": {
            "default": {
              "url": "https://i.ytimg.com/vi/anxiiPGlFfM/default.jpg",
              "width": 120,
              "height": 90
            },
            "medium": {
              "url": "https://i.ytimg.com/vi/anxiiPGlFfM/mqdefault.jpg",
              "width": 320,
              "height": 180
            },
            "high": {
              "url": "https://i.ytimg.com/vi/anxiiPGlFfM/hqdefault.jpg",
              "width": 480,
              "height": 360
            },
            "standard": {
              "url": "https://i.ytimg.com/vi/anxiiPGlFfM/sddefault.jpg",
              "width": 640,
              "height": 480
            },
            "maxres": {
              "url": "https://i.ytimg.com/vi/anxiiPGlFfM/maxresdefault.jpg",
              "width": 1280,
              "height": 720
            }
          },
          "channelTitle": "F4WOnline",
          "tags": [
            "wrestling observer",
            "dave meltzer",
            "bryan alvarez",
            "wrestling observer live",
            "f4wonline",
            "wwe",
            "aew",
            "bryan and vinny",
            "wrestlemania",
            "f4w",
            "figure four",
            "figure four online",
            "Brian Alvarez",
            "Meltzer",
            "Wrestling observer radio",
            "Wrestling observer live"
          ],
          "categoryId": "17",
          "liveBroadcastContent": "none",
          "defaultLanguage": "en",
          "localized": {
            "title": "What does the WarnerMedia-Discovery merger mean for AEW?: Wrestling Observer Radio",
            "description": "Now that WarnerMedia and Discovery have merged to form Warner Bros. Discovery, Bryan and Dave discuss what it could mean for AEW's television deal with WarnerMedia. [April 12, 2022]\n\nDon't have access to this video? Sign up now! https://www.youtube.com/channel/UCPcc1MbakHpB8F1vIDvUJBg/join\n\nYou can see the Wrestling Observer Newsletter with a subscription here: http://account.f4wonline.com/signup\n\nWrestling Observer is live at Noon PST/3pm EST every weekday, live on Twitch! https://twitch.tv/f4wvideo \n\nGrab some awesome T Shirts here: https://www.f4wonline.com/shirts\n\nFollowing us on Twitter @WONF4W https://twitter.com/wonf4w"
          },
          "defaultAudioLanguage": "en"
        },
        "contentDetails": {
          "duration": "PT6M43S",
          "dimension": "2d",
          "definition": "hd",
          "caption": "false",
          "licensedContent": true,
          "contentRating": {},
          "projection": "rectangular"
        },
        "statistics": {
          "viewCount": "24782",
          "likeCount": "630",
          "favoriteCount": "0",
          "commentCount": "352"
        }
      },
      {
        "kind": "youtube#video",
        "etag": "gC8NeXlI6FwxQCNBodVRvX-JUq0",
        "id": "dBUhiQUGYg8",
        "snippet": {
          "publishedAt": "2022-02-04T19:06:38Z",
          "channelId": "UCgCh-2AfEBtWrNBC2OoNQYg",
          "title": "BIG AT&T STOCK NEWS! | AT&T Stock Analysis |",
          "description": "Link to download my portfolio tracking spreadsheets:\nhttps://www.patreon.com/dividendology\n\nIn this video, we cover some new AT&T stock news and do a deep dive into the intrinsic value of AT&T. We use the new information given to us by AT&T to perform a discounted cash flow analysis and a dividend discount model. Are you going to be buying AT&T stock? Let me know your thoughts in the description!\n\nGet one free stock when you sign up for robinhood at this link: https://join.robinhood.com/elib190\n\nI am not a Financial advisor or licensed professional. Nothing I say or produce on YouTube, or anywhere else, should be considered as advice. All content is for educational purposes only. I am not responsible for any financial losses or gains. Invest and trade at your own risk. Some of the links in the description may be affiliate links.",
          "thumbnails": {
            "default": {
              "url": "https://i.ytimg.com/vi/dBUhiQUGYg8/default.jpg",
              "width": 120,
              "height": 90
            },
            "medium": {
              "url": "https://i.ytimg.com/vi/dBUhiQUGYg8/mqdefault.jpg",
              "width": 320,
              "height": 180
            },
            "high": {
              "url": "https://i.ytimg.com/vi/dBUhiQUGYg8/hqdefault.jpg",
              "width": 480,
              "height": 360
            },
            "standard": {
              "url": "https://i.ytimg.com/vi/dBUhiQUGYg8/sddefault.jpg",
              "width": 640,
              "height": 480
            }
          },
          "channelTitle": "Dividendology",
          "tags": [
            "stock market",
            "t stock",
            "at&t stock",
            "stocks",
            "stock",
            "at&t stock analysis",
            "t stock analysis",
            "stock market news",
            "at&t stock dividend",
            "fundamental stock analysis",
            "stock fundamental analysis",
            "dividend stocks",
            "at&t stock price",
            "fundamentals of a stock",
            "finance stock",
            "att stock",
            "stock trading for beginners",
            "t stock 2021",
            "is t stock a buy",
            "stock analysis",
            "at&t stock 2021",
            "is at&t stock a buy",
            "at&t stock news",
            "t stock dividend",
            "at&t stock 2022",
            "at&t stock analysis 2022"
          ],
          "categoryId": "27",
          "liveBroadcastContent": "none",
          "defaultLanguage": "en",
          "localized": {
            "title": "BIG AT&T STOCK NEWS! | AT&T Stock Analysis |",
            "description": "Link to download my portfolio tracking spreadsheets:\nhttps://www.patreon.com/dividendology\n\nIn this video, we cover some new AT&T stock news and do a deep dive into the intrinsic value of AT&T. We use the new information given to us by AT&T to perform a discounted cash flow analysis and a dividend discount model. Are you going to be buying AT&T stock? Let me know your thoughts in the description!\n\nGet one free stock when you sign up for robinhood at this link: https://join.robinhood.com/elib190\n\nI am not a Financial advisor or licensed professional. Nothing I say or produce on YouTube, or anywhere else, should be considered as advice. All content is for educational purposes only. I am not responsible for any financial losses or gains. Invest and trade at your own risk. Some of the links in the description may be affiliate links."
          }
        },
        "contentDetails": {
          "duration": "PT6M39S",
          "dimension": "2d",
          "definition": "hd",
          "caption": "false",
          "licensedContent": true,
          "contentRating": {},
          "projection": "rectangular"
        },
        "statistics": {
          "viewCount": "6230",
          "likeCount": "143",
          "favoriteCount": "0",
          "commentCount": "32"
        }
      },
      {
        "kind": "youtube#video",
        "etag": "-sRm-UfAFuIOm7NWKRIOf33-Wcg",
        "id": "XiTqEXr5Uws",
        "snippet": {
          "publishedAt": "2022-02-27T12:33:43Z",
          "channelId": "UCatSwCHVd7hhEVOoQnODfVg",
          "title": "Warner Bros Discovery - Stock Analysis - $WBD",
          "description": "$WBD Warner Bros Discovery is a global entertainment company that produces TV networks, feature length theatrical releases, as well operates streaming platforms. In this stream, I summarize my analysis of their business and valuation of their stock in consideration for my own investment portfolio.\n\n00:00:00 Intro/Spin-off-Merger\n00:06:05 Prep\n00:11:30 Number Crunching\n00:35:10 5-year Trend\n01:06:00 Historical Analysis\n01:09:55 Future Assumptions\n01:28:40 Valuation\n01:37:50 Schedule/Outro\n\nDisclaimer:\nThis is not investment advise. I am merely operating my own portfolio publicly as a personal academic exercise and viewers should take my experience as just that, one person's experience. Investing in the stock market is risky, please consult with a licensed adviser before doing so.\n\nCome watch me value companies live\nYoutube: https://www.youtube.com/channel/UCatSwCHVd7hhEVOoQnODfVg\nTwitch: https://www.twitch.tv/midasmoriarty\nDiscord: https://discord.gg/DHb3DrUjZk\nOther Links: https://linktr.ee/MidasMoriarty\n\nSupport the stream: https://streamlabs.com/midasmoriartyinvesting",
          "thumbnails": {
            "default": {
              "url": "https://i.ytimg.com/vi/XiTqEXr5Uws/default.jpg",
              "width": 120,
              "height": 90
            },
            "medium": {
              "url": "https://i.ytimg.com/vi/XiTqEXr5Uws/mqdefault.jpg",
              "width": 320,
              "height": 180
            },
            "high": {
              "url": "https://i.ytimg.com/vi/XiTqEXr5Uws/hqdefault.jpg",
              "width": 480,
              "height": 360
            },
            "standard": {
              "url": "https://i.ytimg.com/vi/XiTqEXr5Uws/sddefault.jpg",
              "width": 640,
              "height": 480
            },
            "maxres": {
              "url": "https://i.ytimg.com/vi/XiTqEXr5Uws/maxresdefault.jpg",
              "width": 1280,
              "height": 720
            }
          },
          "channelTitle": "Midas Investing",
          "tags": [
            "live",
            "valuation",
            "value",
            "investing",
            "stock",
            "market",
            "stonks",
            "dcf",
            "discounted",
            "cash",
            "flow",
            "google",
            "sheets",
            "excel",
            "spreadsheet",
            "10k",
            "earnings",
            "call",
            "revenue",
            "margins",
            "capital",
            "ratios",
            "$disca",
            "$discb",
            "disca",
            "discb",
            "discovery",
            "plus",
            "disney",
            "dis",
            "$dis",
            "merger",
            "att",
            "at&t",
            "$t",
            "warner",
            "bros",
            "warnermedia",
            "spinoff",
            "netflix",
            "nflx",
            "$nflx",
            "hbo",
            "max"
          ],
          "categoryId": "24",
          "liveBroadcastContent": "none",
          "defaultLanguage": "en",
          "localized": {
            "title": "Warner Bros Discovery - Stock Analysis - $WBD",
            "description": "$WBD Warner Bros Discovery is a global entertainment company that produces TV networks, feature length theatrical releases, as well operates streaming platforms. In this stream, I summarize my analysis of their business and valuation of their stock in consideration for my own investment portfolio.\n\n00:00:00 Intro/Spin-off-Merger\n00:06:05 Prep\n00:11:30 Number Crunching\n00:35:10 5-year Trend\n01:06:00 Historical Analysis\n01:09:55 Future Assumptions\n01:28:40 Valuation\n01:37:50 Schedule/Outro\n\nDisclaimer:\nThis is not investment advise. I am merely operating my own portfolio publicly as a personal academic exercise and viewers should take my experience as just that, one person's experience. Investing in the stock market is risky, please consult with a licensed adviser before doing so.\n\nCome watch me value companies live\nYoutube: https://www.youtube.com/channel/UCatSwCHVd7hhEVOoQnODfVg\nTwitch: https://www.twitch.tv/midasmoriarty\nDiscord: https://discord.gg/DHb3DrUjZk\nOther Links: https://linktr.ee/MidasMoriarty\n\nSupport the stream: https://streamlabs.com/midasmoriartyinvesting"
          },
          "defaultAudioLanguage": "en-US"
        },
        "contentDetails": {
          "duration": "PT1H39M7S",
          "dimension": "2d",
          "definition": "hd",
          "caption": "false",
          "licensedContent": false,
          "contentRating": {},
          "projection": "rectangular"
        },
        "statistics": {
          "viewCount": "284",
          "likeCount": "6",
          "favoriteCount": "0",
          "commentCount": "2"
        }
      },
      {
        "kind": "youtube#video",
        "etag": "Pjg3g--YIUDWKlWO51pdpcTgxgk",
        "id": "cGZboJ7hZMk",
        "snippet": {
          "publishedAt": "2022-02-03T00:08:28Z",
          "channelId": "UCHDRBmhUBNr5gZLpLZ1pi6Q",
          "title": "GE Still Has a Long Ways to Go | GE Stock Analysis",
          "description": "In this video, I reviewed GE's most recent Earnings updates and the current financial position and value of the stock.\n\n\n\nGet a Free Stock Buy Signing Up For Robinhood!\nhttps://join.robinhood.com/nichold83\n\nP/E Calculator\nhttps://docs.google.com/spreadsheets/d/1SSI7dE1NENgrPB7x2_Nuf5WpcIPzoICP_oahOKK_W2g/edit#gid=142567238\n\n\nDISCLAIMER: I am not a financial advisor. These videos are for educational purposes only. Investing of any kind involves risk. Your investments are solely your responsibility. It is crucial that you conduct your own research. I am merely sharing my opinion with no guarantee of gains or losses on investments. Please consult your financial or tax professional prior to making an investment.",
          "thumbnails": {
            "default": {
              "url": "https://i.ytimg.com/vi/cGZboJ7hZMk/default.jpg",
              "width": 120,
              "height": 90
            },
            "medium": {
              "url": "https://i.ytimg.com/vi/cGZboJ7hZMk/mqdefault.jpg",
              "width": 320,
              "height": 180
            },
            "high": {
              "url": "https://i.ytimg.com/vi/cGZboJ7hZMk/hqdefault.jpg",
              "width": 480,
              "height": 360
            },
            "standard": {
              "url": "https://i.ytimg.com/vi/cGZboJ7hZMk/sddefault.jpg",
              "width": 640,
              "height": 480
            },
            "maxres": {
              "url": "https://i.ytimg.com/vi/cGZboJ7hZMk/maxresdefault.jpg",
              "width": 1280,
              "height": 720
            }
          },
          "channelTitle": "Nick Daly",
          "tags": [
            "general electric stock",
            "ge stock",
            "stock market",
            "general electric",
            "ge stock analysis",
            "general electric stock analysis",
            "finance stock",
            "financial education",
            "ge stock price forecast",
            "ge stock price",
            "ge stock news",
            "is ge stock a buy",
            "should i buy ge stock",
            "ge stock split",
            "is ge stock a good buy",
            "buying ge stock",
            "ge stock earnings",
            "ge\u00a0stock",
            "ge stock analysis 2021",
            "ge stock today",
            "ge reverse stock split",
            "ge power stock",
            "ge power stock analysis"
          ],
          "categoryId": "26",
          "liveBroadcastContent": "none",
          "defaultLanguage": "en",
          "localized": {
            "title": "GE Still Has a Long Ways to Go | GE Stock Analysis",
            "description": "In this video, I reviewed GE's most recent Earnings updates and the current financial position and value of the stock.\n\n\n\nGet a Free Stock Buy Signing Up For Robinhood!\nhttps://join.robinhood.com/nichold83\n\nP/E Calculator\nhttps://docs.google.com/spreadsheets/d/1SSI7dE1NENgrPB7x2_Nuf5WpcIPzoICP_oahOKK_W2g/edit#gid=142567238\n\n\nDISCLAIMER: I am not a financial advisor. These videos are for educational purposes only. Investing of any kind involves risk. Your investments are solely your responsibility. It is crucial that you conduct your own research. I am merely sharing my opinion with no guarantee of gains or losses on investments. Please consult your financial or tax professional prior to making an investment."
          },
          "defaultAudioLanguage": "en-US"
        },
        "contentDetails": {
          "duration": "PT2M43S",
          "dimension": "2d",
          "definition": "hd",
          "caption": "true",
          "licensedContent": false,
          "contentRating": {},
          "projection": "rectangular"
        },
        "statistics": {
          "viewCount": "295",
          "likeCount": "7",
          "favoriteCount": "0",
          "commentCount": "1"
        }
      },
      {
        "kind": "youtube#video",
        "etag": "0N5BVciipro9nUWNC8A2Cdl8F9U",
        "id": "08AUMLea6mk",
        "snippet": {
          "publishedAt": "2022-10-01T20:00:00Z",
          "channelId": "UChBVf9YnourrEDTsbbwJPRA",
          "title": "3 stocks at 52 Wk Low! | Mastercard, AT&T, UPS stock analysis",
          "description": "Today, I'm going to analyze 3 stocks at 52 wk low. We'll get into the fundamentals of Mastercard, AT&T and UPS stock to see if they are good stocks to buy now.\n\n#52weeklow #mastercard #upsstock\n\n0:00 Mastercard financials \n1:56 10 year analysis of MA stock\n3:27 AT&T stock review and debt analysis\n7:01 UPS stock analysis and target price\n9:27 Stocks are susceptible to big falls\n\nJoin the community of like-minded investors: \nhttps://everythingmoney.com/store  OR\nhttps://www.patreon.com/everythingmoney\n_____________________________________________________\n\u26a0\ufe0f By watching videos posted on Everything Money\u2019s YouTube channel and/or using EverythingMoney.com, you acknowledge that you have read, understand, and agree to the following:\n\nEverything Money is Not an Investment Advisor: Everything Money (including Paul, Mo, and Seth) is not an investment adviser, and it is not registered as such with the U.S. Securities & Exchange Commission or any other state or federal authority under the Investment Advisers Act of 1940 or any other law. The investments and strategies discussed in Everything Money\u2019s YouTube videos and on Everythingmoney.com are not and should not be considered investment advice and may not be suitable for you. They do not take into account your particular investment objectives, financial situation, needs, or personal circumstances and are not intended to be specific to you. Before acting on any investment or strategy discussed, you should always do your own research and make your own independent decision about whether it is suitable for your particular circumstances. You should also consider seeking advice from your own legal, financial, tax, accounting, or investment advisers. Everything Money does not provide such advice.\n\nREAD THE FULL DISCLAIMER HERE: https://everythingmoney.com/disclaimer",
          "thumbnails": {
            "default": {
              "url": "https://i.ytimg.com/vi/08AUMLea6mk/default.jpg",
              "width": 120,
              "height": 90
            },
            "medium": {
              "url": "https://i.ytimg.com/vi/08AUMLea6mk/mqdefault.jpg",
              "width": 320,
              "height": 180
            },
            "high": {
              "url": "https://i.ytimg.com/vi/08AUMLea6mk/hqdefault.jpg",
              "width": 480,
              "height": 360
            },
            "standard": {
              "url": "https://i.ytimg.com/vi/08AUMLea6mk/sddefault.jpg",
              "width": 640,
              "height": 480
            },
            "maxres": {
              "url": "https://i.ytimg.com/vi/08AUMLea6mk/maxresdefault.jpg",
              "width": 1280,
              "height": 720
            }
          },
          "channelTitle": "Everything Money",
          "tags": [
            "stock",
            "stock market",
            "stocks",
            "stocks to buy",
            "everything money",
            "investing",
            "financial education",
            "value investing",
            "stocks to buy now",
            "stocks 2022",
            "value investing vs growth investing",
            "stocks channel",
            "3 stocks at 52 Wk Low! | Mastercard",
            "AT&T",
            "UPS stock analysis",
            "3 stocks at 52 wk low",
            "3 stocks",
            "stocks at 52 wk low",
            "mastercard stock",
            "at&t stock",
            "t stock",
            "at&t stock analysis",
            "ups",
            "ups stock",
            "paul gabrail"
          ],
          "categoryId": "27",
          "liveBroadcastContent": "none",
          "defaultLanguage": "en-US",
          "localized": {
            "title": "3 stocks at 52 Wk Low! | Mastercard, AT&T, UPS stock analysis",
            "description": "Today, I'm going to analyze 3 stocks at 52 wk low. We'll get into the fundamentals of Mastercard, AT&T and UPS stock to see if they are good stocks to buy now.\n\n#52weeklow #mastercard #upsstock\n\n0:00 Mastercard financials \n1:56 10 year analysis of MA stock\n3:27 AT&T stock review and debt analysis\n7:01 UPS stock analysis and target price\n9:27 Stocks are susceptible to big falls\n\nJoin the community of like-minded investors: \nhttps://everythingmoney.com/store  OR\nhttps://www.patreon.com/everythingmoney\n_____________________________________________________\n\u26a0\ufe0f By watching videos posted on Everything Money\u2019s YouTube channel and/or using EverythingMoney.com, you acknowledge that you have read, understand, and agree to the following:\n\nEverything Money is Not an Investment Advisor: Everything Money (including Paul, Mo, and Seth) is not an investment adviser, and it is not registered as such with the U.S. Securities & Exchange Commission or any other state or federal authority under the Investment Advisers Act of 1940 or any other law. The investments and strategies discussed in Everything Money\u2019s YouTube videos and on Everythingmoney.com are not and should not be considered investment advice and may not be suitable for you. They do not take into account your particular investment objectives, financial situation, needs, or personal circumstances and are not intended to be specific to you. Before acting on any investment or strategy discussed, you should always do your own research and make your own independent decision about whether it is suitable for your particular circumstances. You should also consider seeking advice from your own legal, financial, tax, accounting, or investment advisers. Everything Money does not provide such advice.\n\nREAD THE FULL DISCLAIMER HERE: https://everythingmoney.com/disclaimer"
          },
          "defaultAudioLanguage": "en-US"
        },
        "contentDetails": {
          "duration": "PT10M32S",
          "dimension": "2d",
          "definition": "hd",
          "caption": "false",
          "licensedContent": true,
          "contentRating": {},
          "projection": "rectangular"
        },
        "statistics": {
          "viewCount": "14035",
          "likeCount": "402",
          "favoriteCount": "0",
          "commentCount": "52"
        }
      },
      {
        "kind": "youtube#video",
        "etag": "cYfo0dPAOqm7S7QUbGIxXpVtcPo",
        "id": "lOBFkxOz7YE",
        "snippet": {
          "publishedAt": "2022-02-10T16:00:17Z",
          "channelId": "UCHDRBmhUBNr5gZLpLZ1pi6Q",
          "title": "SNAP Stock Is Headed Higher | SNAP Stock Analysis",
          "description": "In this video, I reviewed SNAP Stock most recent Earnings updates and the current financial position and value of the stock.\n\n\n\nGet a Free Stock Buy Signing Up For Robinhood!\nhttps://join.robinhood.com/nichold83\n\nP/E Calculator\nhttps://docs.google.com/spreadsheets/d/1SSI7dE1NENgrPB7x2_Nuf5WpcIPzoICP_oahOKK_W2g/edit#gid=142567238\n\n\nDISCLAIMER: I am not a financial advisor. These videos are for educational purposes only. Investing of any kind involves risk. Your investments are solely your responsibility. It is crucial that you conduct your own research. I am merely sharing my opinion with no guarantee of gains or losses on investments. Please consult your financial or tax professional prior to making an investment.",
          "thumbnails": {
            "default": {
              "url": "https://i.ytimg.com/vi/lOBFkxOz7YE/default.jpg",
              "width": 120,
              "height": 90
            },
            "medium": {
              "url": "https://i.ytimg.com/vi/lOBFkxOz7YE/mqdefault.jpg",
              "width": 320,
              "height": 180
            },
            "high": {
              "url": "https://i.ytimg.com/vi/lOBFkxOz7YE/hqdefault.jpg",
              "width": 480,
              "height": 360
            },
            "standard": {
              "url": "https://i.ytimg.com/vi/lOBFkxOz7YE/sddefault.jpg",
              "width": 640,
              "height": 480
            },
            "maxres": {
              "url": "https://i.ytimg.com/vi/lOBFkxOz7YE/maxresdefault.jpg",
              "width": 1280,
              "height": 720
            }
          },
          "channelTitle": "Nick Daly",
          "tags": [
            "snap stock",
            "snapchat stock",
            "snap stock analysis",
            "snap stock forecast",
            "snap stock news",
            "snapchat stock analysis",
            "should i buy snapchat stock",
            "snapchat stock today",
            "snap stock review",
            "snap stock buy"
          ],
          "categoryId": "26",
          "liveBroadcastContent": "none",
          "defaultLanguage": "en",
          "localized": {
            "title": "SNAP Stock Is Headed Higher | SNAP Stock Analysis",
            "description": "In this video, I reviewed SNAP Stock most recent Earnings updates and the current financial position and value of the stock.\n\n\n\nGet a Free Stock Buy Signing Up For Robinhood!\nhttps://join.robinhood.com/nichold83\n\nP/E Calculator\nhttps://docs.google.com/spreadsheets/d/1SSI7dE1NENgrPB7x2_Nuf5WpcIPzoICP_oahOKK_W2g/edit#gid=142567238\n\n\nDISCLAIMER: I am not a financial advisor. These videos are for educational purposes only. Investing of any kind involves risk. Your investments are solely your responsibility. It is crucial that you conduct your own research. I am merely sharing my opinion with no guarantee of gains or losses on investments. Please consult your financial or tax professional prior to making an investment."
          },
          "defaultAudioLanguage": "en-US"
        },
        "contentDetails": {
          "duration": "PT4M18S",
          "dimension": "2d",
          "definition": "hd",
          "caption": "true",
          "licensedContent": false,
          "contentRating": {},
          "projection": "rectangular"
        },
        "statistics": {
          "viewCount": "101",
          "likeCount": "2",
          "favoriteCount": "0",
          "commentCount": "4"
        }
      },
      {
        "kind": "youtube#video",
        "etag": "hFLUBNqgyQEnp6Myirl22tK-obE",
        "id": "fc260Ke6Zk8",
        "snippet": {
          "publishedAt": "2022-02-06T16:53:19Z",
          "channelId": "UCbcB_-Hn75TrZUP4nZX4jow",
          "title": "#DWAC \ud83d\udd25Trump Social Media App Launch Soon! #DWACW \ud83d\udd25 #PHUN \ud83d\udd25 #CFVI \ud83d\udd25 Should you enter before run-up?",
          "description": "#DWAC  #PHUN  #CFVI\nPlease join my Patreon and get access to Discord to get daily trade ideas, instant notifications, and live chat!  https://www.patreon.com/dastockanalyst \n_____________________________________________\n \u26a0\ufe0f DISCLAIMER: \u26a0\ufe0f \nPlease note that  \"I AM NOT A FINANCIAL ADVISOR\". This videos presents  my personal thoughts only and made for entertainment purpose only! You should be responsible for your own trade and if you profit or lose money, the entire responsibility/credit goes to you. Therefore, without blindly following any comment/post/alert, make your own plan for the trade. \"Plan your Trade and Trade your Plan\". \n_____________________________________________\n#DWAC \ud83d\udd25Trump Social Media App Launch Soon! #DWACW \ud83d\udd25 #PHUN \ud83d\udd25 #CFVI \ud83d\udd25 \n--------------------------------------------------------------------\nPlease join my Patreon and get access to Discord to get daily trade ideas, instant notifications, and live chat! \nhttps://www.patreon.com/dastockanalyst \n----------------------------------------------------------------------\nJoin my youtube community   to get daily trade ideas, and access to charts, videos, and news:\nhttps://www.youtube.com/channel/UCbcB_-Hn75TrZUP4nZX4jow/join\n----------------------------------------------------------------------\nWant free money for buying crypto? use my referral link below for creating new account:\nCoinbase link: http://coinbase.com/join/alam_km4?src...\nBinance link: https://www.binance.com/en/register?r...\nCrypto: com link: https://platinum.crypto.com/r/yjfrgvt9c4\nBlockFI link: https://blockfi.com/?ref=91b795e9\n----------------------------------------------------------------------\nin Canada? If you prefer to buy Option for $1 commission, try the Interactive Broker link below https://ibkr.com/referral/ahsan131\n---------------------------------------------------------------------\nJoin my SOCIAL media channels:\nhttps://twitter.com/DaStockAnalyst\nhttps://stocktwits.com/DaStockAnalyst_\n----------------------------------------------------------------------\nFor charting use the following TradingView link, we get benefits for using the link:https://www.tradingview.com/gopro/?share_your_love=ahsan26",
          "thumbnails": {
            "default": {
              "url": "https://i.ytimg.com/vi/fc260Ke6Zk8/default.jpg",
              "width": 120,
              "height": 90
            },
            "medium": {
              "url": "https://i.ytimg.com/vi/fc260Ke6Zk8/mqdefault.jpg",
              "width": 320,
              "height": 180
            },
            "high": {
              "url": "https://i.ytimg.com/vi/fc260Ke6Zk8/hqdefault.jpg",
              "width": 480,
              "height": 360
            },
            "standard": {
              "url": "https://i.ytimg.com/vi/fc260Ke6Zk8/sddefault.jpg",
              "width": 640,
              "height": 480
            },
            "maxres": {
              "url": "https://i.ytimg.com/vi/fc260Ke6Zk8/maxresdefault.jpg",
              "width": 1280,
              "height": 720
            }
          },
          "channelTitle": "Da Stock Analyst",
          "tags": [
            "phun",
            "dwac",
            "phun stock",
            "phun share",
            "dwac stock",
            "dwac share",
            "trump stock",
            "trump dwac",
            "digital world stock",
            "bene share",
            "dwacw",
            "dwac warrants",
            "mark share",
            "trump media stocks",
            "hot stocks",
            "cfvi",
            "cfviw",
            "trump social media app",
            "truth social"
          ],
          "categoryId": "24",
          "liveBroadcastContent": "none",
          "defaultLanguage": "en",
          "localized": {
            "title": "#DWAC \ud83d\udd25Trump Social Media App Launch Soon! #DWACW \ud83d\udd25 #PHUN \ud83d\udd25 #CFVI \ud83d\udd25 Should you enter before run-up?",
            "description": "#DWAC  #PHUN  #CFVI\nPlease join my Patreon and get access to Discord to get daily trade ideas, instant notifications, and live chat!  https://www.patreon.com/dastockanalyst \n_____________________________________________\n \u26a0\ufe0f DISCLAIMER: \u26a0\ufe0f \nPlease note that  \"I AM NOT A FINANCIAL ADVISOR\". This videos presents  my personal thoughts only and made for entertainment purpose only! You should be responsible for your own trade and if you profit or lose money, the entire responsibility/credit goes to you. Therefore, without blindly following any comment/post/alert, make your own plan for the trade. \"Plan your Trade and Trade your Plan\". \n_____________________________________________\n#DWAC \ud83d\udd25Trump Social Media App Launch Soon! #DWACW \ud83d\udd25 #PHUN \ud83d\udd25 #CFVI \ud83d\udd25 \n--------------------------------------------------------------------\nPlease join my Patreon and get access to Discord to get daily trade ideas, instant notifications, and live chat! \nhttps://www.patreon.com/dastockanalyst \n----------------------------------------------------------------------\nJoin my youtube community   to get daily trade ideas, and access to charts, videos, and news:\nhttps://www.youtube.com/channel/UCbcB_-Hn75TrZUP4nZX4jow/join\n----------------------------------------------------------------------\nWant free money for buying crypto? use my referral link below for creating new account:\nCoinbase link: http://coinbase.com/join/alam_km4?src...\nBinance link: https://www.binance.com/en/register?r...\nCrypto: com link: https://platinum.crypto.com/r/yjfrgvt9c4\nBlockFI link: https://blockfi.com/?ref=91b795e9\n----------------------------------------------------------------------\nin Canada? If you prefer to buy Option for $1 commission, try the Interactive Broker link below https://ibkr.com/referral/ahsan131\n---------------------------------------------------------------------\nJoin my SOCIAL media channels:\nhttps://twitter.com/DaStockAnalyst\nhttps://stocktwits.com/DaStockAnalyst_\n----------------------------------------------------------------------\nFor charting use the following TradingView link, we get benefits for using the link:https://www.tradingview.com/gopro/?share_your_love=ahsan26"
          },
          "defaultAudioLanguage": "en"
        },
        "contentDetails": {
          "duration": "PT10M45S",
          "dimension": "2d",
          "definition": "hd",
          "caption": "false",
          "licensedContent": true,
          "contentRating": {},
          "projection": "rectangular"
        },
        "statistics": {
          "viewCount": "791",
          "likeCount": "33",
          "favoriteCount": "0",
          "commentCount": "13"
        }
      }
    ],
    "pageInfo": {
      "totalResults": 13,
      "resultsPerPage": 13
    }
  }
}